mlpipeline_analyzer
